Workbook

Sheet Inputs
A1: CLARA — Model Inputs (edit the yellow cells)
A2: Pricing (net, ex-VAT)
A3: Starter price / mo | B3: 690
A4: Growth price / mo | B4: 1990
A5: Enterprise price / mo | B5: 5000
A6: Usage
A7: Starter avg signals / mo | B7: 3000
A8: Growth avg signals / mo | B8: 30000
A9: Enterprise avg signals / mo | B9: 150000
A10: Inference cost per 1,000 signals | B10: 2
A11: Economics
A12: Payment / MoR fee % | B12: 0.05
A13: Annual prepay discount % | B13: 0.17
A14: % customers on annual billing | B14: 0.6
A15: Effective price factor | B15: =1-B14*B13
A16: Churn (monthly logo)
A17: Starter monthly churn | B17: 0.03
A18: Growth monthly churn | B18: 0.02
A19: Enterprise monthly churn | B19: 0.01
A20: Costs & cash
A21: Founder draw / mo | B21: 3500
A22: Tool stack / mo | B22: 300
A23: Starting cash | B23: 20000
A24: Overage per 1,000 signals (info) | B24: 12

Sheet Unit Economics
A1: Per-Tier Unit Economics (monthly)
B3: Starter | C3: Growth | D3: Enterprise
A4: Price / mo | B4: =Inputs!B3 | C4: =Inputs!B4 | D4: =Inputs!B5
A5: Avg signals / mo | B5: =Inputs!B7 | C5: =Inputs!B8 | D5: =Inputs!B9
A6: Inference COGS / mo | B6: =B5/1000*Inputs!$B$10 | C6: =C5/1000*Inputs!$B$10 | D6: =D5/1000*Inputs!$B$10
A7: Payment fee / mo | B7: =B4*Inputs!$B$12 | C7: =C4*Inputs!$B$12 | D7: =D4*Inputs!$B$12
A8: Gross profit / mo | B8: =B4-B6-B7 | C8: =C4-C6-C7 | D8: =D4-D6-D7
A9: Gross margin % | B9: =B8/B4 | C9: =C8/C4 | D9: =D8/D4
A10: Monthly churn | B10: =Inputs!B17 | C10: =Inputs!B18 | D10: =Inputs!B19
A11: Avg lifetime (mo) | B11: =1/B10 | C11: =1/C10 | D11: =1/D10
A12: LTV (gross) | B12: =B8*B11 | C12: =C8*C11 | D12: =D8*D11

Sheet 24-Month Projection
A1: 24-Month Projection (edit new-customer columns)
A3: Month | B3: New S | C3: New G | D3: New E | E3: Active S | F3: Active G | G3: Active E | H3: MRR | I3: ARR | J3: COGS | K3: Gross profit | L3: Opex | M3: Net | N3: Cum. cash
A4: 1 | B4: 1 | C4: 0 | D4: 0 | E4: =B4 | F4: =C4 | G4: =D4 | H4: =(E4*Inputs!$B$3+F4*Inputs!$B$4+G4*Inputs!$B$5)*Inputs!$B$15 | I4: =H4*12 | J4: =(E4*Inputs!$B$7+F4*Inputs!$B$8+G4*Inputs!$B$9)/1000*Inputs!$B$10 | K4: =H4-J4-H4*Inputs!$B$12 | L4: =Inputs!$B$21+Inputs!$B$22 | M4: =K4-L4 | N4: =Inputs!$B$23+M4
A5: 2 | B5: 1 | C5: 1 | D5: 0 | E5: =E4*(1-Inputs!$B$17)+B5 | F5: =F4*(1-Inputs!$B$18)+C5 | G5: =G4*(1-Inputs!$B$19)+D5 | H5: =(E5*Inputs!$B$3+F5*Inputs!$B$4+G5*Inputs!$B$5)*Inputs!$B$15 | I5: =H5*12 | J5: =(E5*Inputs!$B$7+F5*Inputs!$B$8+G5*Inputs!$B$9)/1000*Inputs!$B$10 | K5: =H5-J5-H5*Inputs!$B$12 | L5: =Inputs!$B$21+Inputs!$B$22 | M5: =K5-L5 | N5: =N4+M5
A6: 3 | B6: 2 | C6: 1 | D6: 0 | E6: =E5*(1-Inputs!$B$17)+B6 | F6: =F5*(1-Inputs!$B$18)+C6 | G6: =G5*(1-Inputs!$B$19)+D6 | H6: =(E6*Inputs!$B$3+F6*Inputs!$B$4+G6*Inputs!$B$5)*Inputs!$B$15 | I6: =H6*12 | J6: =(E6*Inputs!$B$7+F6*Inputs!$B$8+G6*Inputs!$B$9)/1000*Inputs!$B$10 | K6: =H6-J6-H6*Inputs!$B$12 | L6: =Inputs!$B$21+Inputs!$B$22 | M6: =K6-L6 | N6: =N5+M6
A7: 4 | B7: 2 | C7: 1 | D7: 0 | E7: =E6*(1-Inputs!$B$17)+B7 | F7: =F6*(1-Inputs!$B$18)+C7 | G7: =G6*(1-Inputs!$B$19)+D7 | H7: =(E7*Inputs!$B$3+F7*Inputs!$B$4+G7*Inputs!$B$5)*Inputs!$B$15 | I7: =H7*12 | J7: =(E7*Inputs!$B$7+F7*Inputs!$B$8+G7*Inputs!$B$9)/1000*Inputs!$B$10 | K7: =H7-J7-H7*Inputs!$B$12 | L7: =Inputs!$B$21+Inputs!$B$22 | M7: =K7-L7 | N7: =N6+M7
A8: 5 | B8: 3 | C8: 1 | D8: 1 | E8: =E7*(1-Inputs!$B$17)+B8 | F8: =F7*(1-Inputs!$B$18)+C8 | G8: =G7*(1-Inputs!$B$19)+D8 | H8: =(E8*Inputs!$B$3+F8*Inputs!$B$4+G8*Inputs!$B$5)*Inputs!$B$15 | I8: =H8*12 | J8: =(E8*Inputs!$B$7+F8*Inputs!$B$8+G8*Inputs!$B$9)/1000*Inputs!$B$10 | K8: =H8-J8-H8*Inputs!$B$12 | L8: =Inputs!$B$21+Inputs!$B$22 | M8: =K8-L8 | N8: =N7+M8
A9: 6 | B9: 3 | C9: 2 | D9: 0 | E9: =E8*(1-Inputs!$B$17)+B9 | F9: =F8*(1-Inputs!$B$18)+C9 | G9: =G8*(1-Inputs!$B$19)+D9 | H9: =(E9*Inputs!$B$3+F9*Inputs!$B$4+G9*Inputs!$B$5)*Inputs!$B$15 | I9: =H9*12 | J9: =(E9*Inputs!$B$7+F9*Inputs!$B$8+G9*Inputs!$B$9)/1000*Inputs!$B$10 | K9: =H9-J9-H9*Inputs!$B$12 | L9: =Inputs!$B$21+Inputs!$B$22 | M9: =K9-L9 | N9: =N8+M9
A10: 7 | B10: 3 | C10: 2 | D10: 0 | E10: =E9*(1-Inputs!$B$17)+B10 | F10: =F9*(1-Inputs!$B$18)+C10 | G10: =G9*(1-Inputs!$B$19)+D10 | H10: =(E10*Inputs!$B$3+F10*Inputs!$B$4+G10*Inputs!$B$5)*Inputs!$B$15 | I10: =H10*12 | J10: =(E10*Inputs!$B$7+F10*Inputs!$B$8+G10*Inputs!$B$9)/1000*Inputs!$B$10 | K10: =H10-J10-H10*Inputs!$B$12 | L10: =Inputs!$B$21+Inputs!$B$22 | M10: =K10-L10 | N10: =N9+M10
A11: 8 | B11: 4 | C11: 2 | D11: 1 | E11: =E10*(1-Inputs!$B$17)+B11 | F11: =F10*(1-Inputs!$B$18)+C11 | G11: =G10*(1-Inputs!$B$19)+D11 | H11: =(E11*Inputs!$B$3+F11*Inputs!$B$4+G11*Inputs!$B$5)*Inputs!$B$15 | I11: =H11*12 | J11: =(E11*Inputs!$B$7+F11*Inputs!$B$8+G11*Inputs!$B$9)/1000*Inputs!$B$10 | K11: =H11-J11-H11*Inputs!$B$12 | L11: =Inputs!$B$21+Inputs!$B$22 | M11: =K11-L11 | N11: =N10+M11
A12: 9 | B12: 4 | C12: 2 | D12: 0 | E12: =E11*(1-Inputs!$B$17)+B12 | F12: =F11*(1-Inputs!$B$18)+C12 | G12: =G11*(1-Inputs!$B$19)+D12 | H12: =(E12*Inputs!$B$3+F12*Inputs!$B$4+G12*Inputs!$B$5)*Inputs!$B$15 | I12: =H12*12 | J12: =(E12*Inputs!$B$7+F12*Inputs!$B$8+G12*Inputs!$B$9)/1000*Inputs!$B$10 | K12: =H12-J12-H12*Inputs!$B$12 | L12: =Inputs!$B$21+Inputs!$B$22 | M12: =K12-L12 | N12: =N11+M12
A13: 10 | B13: 4 | C13: 2 | D13: 0 | E13: =E12*(1-Inputs!$B$17)+B13 | F13: =F12*(1-Inputs!$B$18)+C13 | G13: =G12*(1-Inputs!$B$19)+D13 | H13: =(E13*Inputs!$B$3+F13*Inputs!$B$4+G13*Inputs!$B$5)*Inputs!$B$15 | I13: =H13*12 | J13: =(E13*Inputs!$B$7+F13*Inputs!$B$8+G13*Inputs!$B$9)/1000*Inputs!$B$10 | K13: =H13-J13-H13*Inputs!$B$12 | L13: =Inputs!$B$21+Inputs!$B$22 | M13: =K13-L13 | N13: =N12+M13
A14: 11 | B14: 5 | C14: 3 | D14: 1 | E14: =E13*(1-Inputs!$B$17)+B14 | F14: =F13*(1-Inputs!$B$18)+C14 | G14: =G13*(1-Inputs!$B$19)+D14 | H14: =(E14*Inputs!$B$3+F14*Inputs!$B$4+G14*Inputs!$B$5)*Inputs!$B$15 | I14: =H14*12 | J14: =(E14*Inputs!$B$7+F14*Inputs!$B$8+G14*Inputs!$B$9)/1000*Inputs!$B$10 | K14: =H14-J14-H14*Inputs!$B$12 | L14: =Inputs!$B$21+Inputs!$B$22 | M14: =K14-L14 | N14: =N13+M14
A15: 12 | B15: 5 | C15: 3 | D15: 0 | E15: =E14*(1-Inputs!$B$17)+B15 | F15: =F14*(1-Inputs!$B$18)+C15 | G15: =G14*(1-Inputs!$B$19)+D15 | H15: =(E15*Inputs!$B$3+F15*Inputs!$B$4+G15*Inputs!$B$5)*Inputs!$B$15 | I15: =H15*12 | J15: =(E15*Inputs!$B$7+F15*Inputs!$B$8+G15*Inputs!$B$9)/1000*Inputs!$B$10 | K15: =H15-J15-H15*Inputs!$B$12 | L15: =Inputs!$B$21+Inputs!$B$22 | M15: =K15-L15 | N15: =N14+M15
A16: 13 | B16: 5 | C16: 3 | D16: 0 | E16: =E15*(1-Inputs!$B$17)+B16 | F16: =F15*(1-Inputs!$B$18)+C16 | G16: =G15*(1-Inputs!$B$19)+D16 | H16: =(E16*Inputs!$B$3+F16*Inputs!$B$4+G16*Inputs!$B$5)*Inputs!$B$15 | I16: =H16*12 | J16: =(E16*Inputs!$B$7+F16*Inputs!$B$8+G16*Inputs!$B$9)/1000*Inputs!$B$10 | K16: =H16-J16-H16*Inputs!$B$12 | L16: =Inputs!$B$21+Inputs!$B$22 | M16: =K16-L16 | N16: =N15+M16
... A27: 24 | B27: 8 | C27: 5 | D27: 0 | E27: =E26*(1-Inputs!$B$17)+B27 | F27: =F26*(1-Inputs!$B$18)+C27 | G27: =G26*(1-Inputs!$B$19)+D27 | H27: =(E27*Inputs!$B$3+F27*Inputs!$B$4+G27*Inputs!$B$5)*Inputs!$B$15 | I27: =H27*12 | J27: =(E27*Inputs!$B$7+F27*Inputs!$B$8+G27*Inputs!$B$9)/1000*Inputs!$B$10 | K27: =H27-J27-H27*Inputs!$B$12 | L27: =Inputs!$B$21+Inputs!$B$22 | M27: =K27-L27 | N27: =N26+M27

Sheet Notes
A1: CLARA financial model — how to use
A3: 1. Edit ONLY the yellow cells (Inputs sheet + the New-customer columns on the Projection).
A4: 2. Everything else is formula-driven and recalculates automatically.
A5: 3. Prices are NET (ex-VAT), strategic hypotheses to validate via willingness-to-pay interviews.
A6: 4. 'Effective price factor' discounts MRR for the share of customers on annual prepay.
A7: 5. Cash is recognised monthly (simplified). Annual prepay actually front-loads cash — a real
A8: cash-flow advantage described in 05-pricing-and-financial-model.md, not modelled here.
A9: 6. Inference COGS assumes CLARA's local-first / no-fine-tune stack keeps cost/1k signals low;
A10: tune 'Inference cost per 1,000 signals' from real usage.
A11: 7. This is a planning model, not a forecast or financial advice.
